qiskit_state_evolution_recorder/__init__.py
qiskit_state_evolution_recorder/__main__.py
qiskit_state_evolution_recorder/animation.py
qiskit_state_evolution_recorder/compatibility.py
qiskit_state_evolution_recorder/demo.qasm
qiskit_state_evolution_recorder/frame_renderer.py
qiskit_state_evolution_recorder/recorder.py
qiskit_state_evolution_recorder/state_evolution.py
qiskit_state_evolution_recorder/backend/__init__.py
qiskit_state_evolution_recorder/backend/backend.py
qiskit_state_evolution_recorder/backend/ffmpeg.py
qiskit_state_evolution_recorder/backend/opencv.py
qiskit_state_evolution_recorder/backend/selection.py
qiskit_state_evolution_recorder-1.0.2.dist-info/licenses/LICENSE
qiskit_state_evolution_recorder-1.0.2.dist-info/METADATA
qiskit_state_evolution_recorder-1.0.2.dist-info/WHEEL
qiskit_state_evolution_recorder-1.0.2.dist-info/entry_points.txt
qiskit_state_evolution_recorder-1.0.2.dist-info/top_level.txt
qiskit_state_evolution_recorder-1.0.2.dist-info/RECORD
