Metadata-Version: 2.4
Name: qiskit-state-evolution-recorder
Version: 1.0.2
Summary: Simple module allowing to record animations to trace changes in qubit states for arbitrary quantum circuits.
Author-email: Dawid Ciepiela <71898979+sarumaj@users.noreply.github.com>
License: BSD 3-Clause License
Project-URL: Homepage, https://github.com/sarumaj/qiskit-state-evolution-recorder
Classifier: Development Status :: 4 - Beta
Classifier: Intended Audience :: Science/Research
Classifier: License :: OSI Approved :: BSD License
Classifier: Programming Language :: Python :: 3
Classifier: Programming Language :: Python :: 3.6
Classifier: Programming Language :: Python :: 3.7
Classifier: Programming Language :: Python :: 3.8
Classifier: Programming Language :: Python :: 3.9
Classifier: Programming Language :: Python :: 3.10
Classifier: Programming Language :: Python :: 3.11
Classifier: Programming Language :: Python :: 3.12
Classifier: Topic :: Scientific/Engineering
Classifier: Topic :: Scientific/Engineering :: Physics
Classifier: Topic :: Scientific/Engineering :: Visualization
Classifier: Topic :: Software Development :: Libraries :: Python Modules
Requires-Python: >=3.6
License-File: LICENSE
Requires-Dist: matplotlib==3.10.8
Requires-Dist: matplotlib-inline==0.2.1
Requires-Dist: numpy<2.4.1
Requires-Dist: qiskit<=2.2.3,>=2.2.3
Requires-Dist: pillow==12.0.0
Requires-Dist: pylatexenc==2.10
Requires-Dist: tqdm==4.67.1
Provides-Extra: opencv
Requires-Dist: opencv-python==4.12.0.88; extra == "opencv"
Provides-Extra: test
Requires-Dist: psutil==7.2.0; extra == "test"
Requires-Dist: pytest==9.0.2; extra == "test"
Requires-Dist: pytest-benchmark==5.2.3; extra == "test"
Dynamic: license-file
